{
  "_doc": "Registre Photobooth IA. Arbo : docs/ia/themes/<theme>/<montage>/ avec avant.jpg, apres.jpg (pour le slider), montage.jpg (optionnel) et extras (autres photos). La galerie affiche un slider par montage ayant avant + apres ; le clic ouvre ia/montage.html?theme=<t>&montage=<m>. Voir README.md.",
  "themes": [
    {
      "slug": "disco",
      "label": "Rétro & Disco",
      "montages": [
        {
          "slug": "exemple-01",
          "label": "Exemple 01",
          "avant": "avant.jpeg",
          "apres": "apres.jpg",
          "montage": "montage.jpg",
          "extras": []
        }
      ]
    },
    {
      "slug": "cartoon",
      "label": "Cartoon / 3D",
      "montages": [
        {
          "slug": "exemple-01",
          "label": "Exemple 01",
          "avant": "avant.jpeg",
          "apres": "apres.jpg",
          "montage": "montage.jpg",
          "extras": []
        }
      ]
    },
    {
      "slug": "avatar",
      "label": "Avatar 3D",
      "montages": [
        {
          "slug": "exemple-01",
          "label": "Exemple 01",
          "avant": "avant.jpeg",
          "apres": "apres.png",
          "montage": "montage.jpg",
          "extras": []
        }
      ]
    },
    {
      "slug": "foot",
      "label": "Supporter / Sport",
      "montages": [
        {
          "slug": "exemple-01",
          "label": "Exemple 01",
          "avant": "avant.jpeg",
          "apres": "apres.png",
          "montage": "montage.jpg",
          "extras": []
        }
      ]
    },
    {
      "slug": "halloween",
      "label": "Halloween",
      "montages": [
        {
          "slug": "exemple-01",
          "label": "Exemple 01",
          "avant": "avant.jpeg",
          "apres": "apres.png",
          "montage": "montage.jpg",
          "extras": []
        }
      ]
    },
    {
      "slug": "super-heros",
      "label": "Super-héros",
      "montages": [
        {
          "slug": "exemple-01",
          "label": "Exemple 01",
          "avant": "avant.jpeg",
          "apres": "apres.png",
          "montage": "montage.jpg",
          "extras": []
        }
      ]
    },
    {
      "slug": "mariage",
      "label": "Mariage",
      "montages": [
        {
          "slug": "exemple-01",
          "label": "Exemple 01",
          "avant": "avant.jpg",
          "apres": "apres.jpg",
          "montage": "montage.jpg",
          "extras": []
        }
      ]
    }
  ]
}
